proton/__init__.py
proton/api.py
proton/cert_pinning.py
proton/constants.py
proton/exceptions.py
proton/doc/conf.py
proton/doc/index.rst
proton/srp/__init__.py
proton/srp/_ctsrp.py
proton/srp/_pysrp.py
proton/srp/pmhash.py
proton/srp/util.py
proton_client-0.5.1.dist-info/COPYING.md
proton_client-0.5.1.dist-info/LICENSE
proton_client-0.5.1.dist-info/METADATA
proton_client-0.5.1.dist-info/WHEEL
proton_client-0.5.1.dist-info/top_level.txt
proton_client-0.5.1.dist-info/RECORD
